__init__.py
tb_device_mqtt.py
tb_gateway_mqtt.py
tb_mqtt_client-1.1.dist-info/LICENSE
tb_mqtt_client-1.1.dist-info/METADATA
tb_mqtt_client-1.1.dist-info/WHEEL
tb_mqtt_client-1.1.dist-info/top_level.txt
tb_mqtt_client-1.1.dist-info/RECORD
