Metadata-Version: 2.1
Name: tb-mqtt-client
Version: 1.1
Summary: ThingsBoard python client SDK
Home-page: https://github.com/thingsboard/thingsboard-python-client-sdk
Author: ThingsBoard
Author-email: info@thingsboard.io
License: Apache Software License (Apache Software License 2.0)
Download-URL: https://github.com/thingsboard/thingsboard-python-client-sdk/archive/1.1.tar.gz
Platform: UNKNOWN
Requires-Python: >=3.5
Requires-Dist: paho-mqtt
Requires-Dist: jsonschema
